uptimer/__init__.py
uptimer/cli.py
uptimer/helpers.py
uptimer-0.1.0.dist-info/AUTHORS.rst
uptimer-0.1.0.dist-info/LICENSE
uptimer-0.1.0.dist-info/METADATA
uptimer-0.1.0.dist-info/WHEEL
uptimer-0.1.0.dist-info/entry_points.txt
uptimer-0.1.0.dist-info/top_level.txt
uptimer-0.1.0.dist-info/RECORD
