Metadata-Version: 2.1
Name: uptimer
Version: 0.1.0
Summary: CLI tool to ping websites and return their HTTP codes.
Home-page: https://github.com/switowski/uptimer
Author: Sebastian Witowski
Author-email: sebastian@switowski.com
License: MIT license
Keywords: uptimer
Platform: UNKNOWN
Classifier: Development Status :: 2 - Pre-Alpha
Classifier: Intended Audience :: Developers
Classifier: License :: OSI Approved :: MIT License
Classifier: Natural Language :: English
Classifier: Programming Language :: Python :: 3
Classifier: Programming Language :: Python :: 3.5
Classifier: Programming Language :: Python :: 3.6
Classifier: Programming Language :: Python :: 3.7
Classifier: Programming Language :: Python :: 3.8
Requires-Python: >=3.5
Requires-Dist: Click (>=7.0)
Requires-Dist: requests (>=2.25)
Requires-Dist: colorama (>=0.4)
